<?xml version="1.0" encoding="UTF-8"?>
<!DOCTYPE tv SYSTEM "xmltv.dtd">

<tv source-info-name="Al Jazeera Balkans guide by TV" source-info-url="https://player.maxtvtogo.tportal.hr:8082/OTT4Proxy/proxy/epg/shows">
  <channel id="AlJazeeraBalkans.qa">
    <display-name>Al Jazeera Balkans</display-name>
    <url>https://balkans.aljazeera.net/live</url>
    <icon src="https://images2.imgbox.com/7e/2e/EnmzsW0o_o.png" />
  </channel>
  <programme channel="AlJazeeraBalkans.qa" start="20230723060000 +0100" stop="20230723080000 +0100">
    <title lang="ba">Al Jazeera English</title>
    <desc lang="ba">Al Jazeera Balkans međunarodna je televizijska postaja mreže Al Jazeera. Dvadeset sati sadržaja postaja samostalno proizvodi na bošnjačkom, hrvatskom i srpskom jeziku, dok ostatak čini program Al Jazeere English. Show Id: 23060227</desc>
    <category lang="ba">ostalo</category>
    <icon src="https://images2.imgbox.com/7e/2e/EnmzsW0o_o.png" />
  </programme>
  <programme channel="AlJazeeraBalkans.qa" start="20230723080000 +0100" stop="20230723083000 +0100">
    <title lang="ba">Al Jazeera Biznis 2023</title>
    <desc lang="ba">Al Jazeera Balkans međunarodna je televizijska postaja mreže Al Jazeera. Dvadeset sati sadržaja postaja samostalno proizvodi na bošnjačkom, hrvatskom i srpskom jeziku, dok ostatak čini program Al Jazeere English. Show Id: 23060230</desc>
    <category lang="ba">Informativni</category>
    <icon src="https://images2.imgbox.com/7e/2e/EnmzsW0o_o.png" />
  </programme>
  <programme channel="AlJazeeraBalkans.qa" start="20230723083000 +0100" stop="20230723090000 +0100">
    <title lang="ba">Granice Istoka</title>
    <desc lang="ba">Al Jazeera Balkans međunarodna je televizijska postaja mreže Al Jazeera. Dvadeset sati sadržaja postaja samostalno proizvodi na bošnjačkom, hrvatskom i srpskom jeziku, dok ostatak čini program Al Jazeere English. Show Id: 23060234</desc>
    <category lang="ba">Dokumentarni</category>
    <icon src="https://images2.imgbox.com/7e/2e/EnmzsW0o_o.png" />
  </programme>
  <programme channel="AlJazeeraBalkans.qa" start="20230723090000 +0100" stop="20230723093000 +0100">
    <title lang="ba">Hoću kući</title>
    <desc lang="ba">Al Jazeera Balkans međunarodna je televizijska postaja mreže Al Jazeera. Dvadeset sati sadržaja postaja samostalno proizvodi na bošnjačkom, hrvatskom i srpskom jeziku, dok ostatak čini program Al Jazeere English. Show Id: 23060236</desc>
    <category lang="ba">Dokumentarni</category>
    <icon src="https://images2.imgbox.com/7e/2e/EnmzsW0o_o.png" />
  </programme>
  <programme channel="AlJazeeraBalkans.qa" start="20230723093000 +0100" stop="20230723100000 +0100">
    <title lang="ba">Kontekst 2023</title>
    <desc lang="ba">Al Jazeera Balkans međunarodna je televizijska postaja mreže Al Jazeera. Dvadeset sati sadržaja postaja samostalno proizvodi na bošnjačkom, hrvatskom i srpskom jeziku, dok ostatak čini program Al Jazeere English. Show Id: 23060239</desc>
    <category lang="ba">Informativni</category>
    <icon src="https://images2.imgbox.com/7e/2e/EnmzsW0o_o.png" />
  </programme>
  <programme channel="AlJazeeraBalkans.qa" start="20230723100000 +0100" stop="20230723103000 +0100">
    <title lang="ba">Al Jazeera Biznis 2023</title>
    <desc lang="ba">Al Jazeera Balkans međunarodna je televizijska postaja mreže Al Jazeera. Dvadeset sati sadržaja postaja samostalno proizvodi na bošnjačkom, hrvatskom i srpskom jeziku, dok ostatak čini program Al Jazeere English. Show Id: 23060243</desc>
    <category lang="ba">Informativni</category>
    <icon src="https://images2.imgbox.com/7e/2e/EnmzsW0o_o.png" />
  </programme>
  <programme channel="AlJazeeraBalkans.qa" start="20230723103000 +0100" stop="20230723110000 +0100">
    <title lang="ba">Kontekst 2023</title>
    <desc lang="ba">Al Jazeera Balkans međunarodna je televizijska postaja mreže Al Jazeera. Dvadeset sati sadržaja postaja samostalno proizvodi na bošnjačkom, hrvatskom i srpskom jeziku, dok ostatak čini program Al Jazeere English. Show Id: 23060247</desc>
    <category lang="ba">Informativni</category>
    <icon src="https://images2.imgbox.com/7e/2e/EnmzsW0o_o.png" />
  </programme>
  <programme channel="AlJazeeraBalkans.qa" start="20230723110000 +0100" stop="20230723120000 +0100">
    <title lang="ba">Bugarski san</title>
    <desc lang="ba">Al Jazeera Balkans međunarodna je televizijska postaja mreže Al Jazeera. Dvadeset sati sadržaja postaja samostalno proizvodi na bošnjačkom, hrvatskom i srpskom jeziku, dok ostatak čini program Al Jazeere English. Show Id: 23060251</desc>
    <category lang="ba">Dokumentarni</category>
    <icon src="https://images2.imgbox.com/7e/2e/EnmzsW0o_o.png" />
  </programme>
  <programme channel="AlJazeeraBalkans.qa" start="20230723120000 +0100" stop="20230723123000 +0100">
    <title lang="ba">Vijesti u 12</title>
    <desc lang="ba">Al Jazeera Balkans međunarodna je televizijska postaja mreže Al Jazeera. Dvadeset sati sadržaja postaja samostalno proizvodi na bošnjačkom, hrvatskom i srpskom jeziku, dok ostatak čini program Al Jazeere English. Show Id: 23060254</desc>
    <category lang="ba">Informativni</category>
    <icon src="https://images2.imgbox.com/7e/2e/EnmzsW0o_o.png" />
  </programme>
  <programme channel="AlJazeeraBalkans.qa" start="20230723123000 +0100" stop="20230723130000 +0100">
    <title lang="ba">#AJBCAFE</title>
    <desc lang="ba">Al Jazeera Balkans međunarodna je televizijska postaja mreže Al Jazeera. Dvadeset sati sadržaja postaja samostalno proizvodi na bošnjačkom, hrvatskom i srpskom jeziku, dok ostatak čini program Al Jazeere English. Show Id: 23060257</desc>
    <category lang="ba">Informativni</category>
    <icon src="https://images2.imgbox.com/7e/2e/EnmzsW0o_o.png" />
  </programme>
  <programme channel="AlJazeeraBalkans.qa" start="20230723130000 +0100" stop="20230723130500 +0100">
    <title lang="ba">Kratke vijesti u 13</title>
    <desc lang="ba">Al Jazeera Balkans međunarodna je televizijska postaja mreže Al Jazeera. Dvadeset sati sadržaja postaja samostalno proizvodi na bošnjačkom, hrvatskom i srpskom jeziku, dok ostatak čini program Al Jazeere English. Show Id: 23060261</desc>
    <category lang="ba">Informativni</category>
    <icon src="https://images2.imgbox.com/7e/2e/EnmzsW0o_o.png" />
  </programme>
  <programme channel="AlJazeeraBalkans.qa" start="20230723130500 +0100" stop="20230723140000 +0100">
    <title lang="ba">Moj život</title>
    <desc lang="ba">Al Jazeera Balkans međunarodna je televizijska postaja mreže Al Jazeera. Dvadeset sati sadržaja postaja samostalno proizvodi na bošnjačkom, hrvatskom i srpskom jeziku, dok ostatak čini program Al Jazeere English. Show Id: 23060264</desc>
    <category lang="ba">Dokumentarni</category>
    <icon src="https://images2.imgbox.com/7e/2e/EnmzsW0o_o.png" />
  </programme>
  <programme channel="AlJazeeraBalkans.qa" start="20230723140000 +0100" stop="20230723143000 +0100">
    <title lang="ba">Vijesti u 14</title>
    <desc lang="ba">Al Jazeera Balkans međunarodna je televizijska postaja mreže Al Jazeera. Dvadeset sati sadržaja postaja samostalno proizvodi na bošnjačkom, hrvatskom i srpskom jeziku, dok ostatak čini program Al Jazeere English. Show Id: 23060267</desc>
    <category lang="ba">Informativni</category>
    <icon src="https://images2.imgbox.com/7e/2e/EnmzsW0o_o.png" />
  </programme>
  <programme channel="AlJazeeraBalkans.qa" start="20230723143000 +0100" stop="20230723150000 +0100">
    <title lang="ba">Al Jazeera Biznis 2023</title>
    <desc lang="ba">Al Jazeera Balkans međunarodna je televizijska postaja mreže Al Jazeera. Dvadeset sati sadržaja postaja samostalno proizvodi na bošnjačkom, hrvatskom i srpskom jeziku, dok ostatak čini program Al Jazeere English. Show Id: 23060271</desc>
    <category lang="ba">Informativni</category>
    <icon src="https://images2.imgbox.com/7e/2e/EnmzsW0o_o.png" />
  </programme>
  <programme channel="AlJazeeraBalkans.qa" start="20230723150000 +0100" stop="20230723153000 +0100">
    <title lang="ba">Vijesti u 15</title>
    <desc lang="ba">Al Jazeera Balkans međunarodna je televizijska postaja mreže Al Jazeera. Dvadeset sati sadržaja postaja samostalno proizvodi na bošnjačkom, hrvatskom i srpskom jeziku, dok ostatak čini program Al Jazeere English. Show Id: 23060274</desc>
    <category lang="ba">Informativni</category>
    <icon src="https://images2.imgbox.com/7e/2e/EnmzsW0o_o.png" />
  </programme>
  <programme channel="AlJazeeraBalkans.qa" start="20230723153000 +0100" stop="20230723160000 +0100">
    <title lang="ba">Slike iz života bh. filma</title>
    <desc lang="ba">Al Jazeera Balkans međunarodna je televizijska postaja mreže Al Jazeera. Dvadeset sati sadržaja postaja samostalno proizvodi na bošnjačkom, hrvatskom i srpskom jeziku, dok ostatak čini program Al Jazeere English. Show Id: 23060277</desc>
    <category lang="ba">Dokumentarni</category>
    <icon src="https://images2.imgbox.com/7e/2e/EnmzsW0o_o.png" />
  </programme>
  <programme channel="AlJazeeraBalkans.qa" start="20230723160000 +0100" stop="20230723170000 +0100">
    <title lang="ba">Vijesti u 16</title>
    <desc lang="ba">Al Jazeera Balkans međunarodna je televizijska postaja mreže Al Jazeera. Dvadeset sati sadržaja postaja samostalno proizvodi na bošnjačkom, hrvatskom i srpskom jeziku, dok ostatak čini program Al Jazeere English. Show Id: 23060281</desc>
    <category lang="ba">Informativni</category>
    <icon src="https://images2.imgbox.com/7e/2e/EnmzsW0o_o.png" />
  </programme>
  <programme channel="AlJazeeraBalkans.qa" start="20230723170000 +0100" stop="20230723170500 +0100">
    <title lang="ba">Kratke vijesti u 17</title>
    <desc lang="ba">Al Jazeera Balkans međunarodna je televizijska postaja mreže Al Jazeera. Dvadeset sati sadržaja postaja samostalno proizvodi na bošnjačkom, hrvatskom i srpskom jeziku, dok ostatak čini program Al Jazeere English. Show Id: 23060283</desc>
    <category lang="ba">Informativni</category>
    <icon src="https://images2.imgbox.com/7e/2e/EnmzsW0o_o.png" />
  </programme>
  <programme channel="AlJazeeraBalkans.qa" start="20230723170500 +0100" stop="20230723173000 +0100">
    <title lang="ba">Imperija &amp; Republika</title>
    <desc lang="ba">Al Jazeera Balkans međunarodna je televizijska postaja mreže Al Jazeera. Dvadeset sati sadržaja postaja samostalno proizvodi na bošnjačkom, hrvatskom i srpskom jeziku, dok ostatak čini program Al Jazeere English. Show Id: 23060286</desc>
    <category lang="ba">ostalo</category>
    <icon src="https://images2.imgbox.com/7e/2e/EnmzsW0o_o.png" />
  </programme>
  <programme channel="AlJazeeraBalkans.qa" start="20230723173000 +0100" stop="20230723180000 +0100">
    <title lang="ba">Jho Low - Lov na bjegunca</title>
    <desc lang="ba">Al Jazeera Balkans međunarodna je televizijska postaja mreže Al Jazeera. Dvadeset sati sadržaja postaja samostalno proizvodi na bošnjačkom, hrvatskom i srpskom jeziku, dok ostatak čini program Al Jazeere English. Show Id: 23060290</desc>
    <category lang="ba">Dokumentarni</category>
    <icon src="https://images2.imgbox.com/7e/2e/EnmzsW0o_o.png" />
  </programme>
  <programme channel="AlJazeeraBalkans.qa" start="20230723180000 +0100" stop="20230723190000 +0100">
    <title lang="ba">Vijesti u 18</title>
    <desc lang="ba">Al Jazeera Balkans međunarodna je televizijska postaja mreže Al Jazeera. Dvadeset sati sadržaja postaja samostalno proizvodi na bošnjačkom, hrvatskom i srpskom jeziku, dok ostatak čini program Al Jazeere English. Show Id: 23060293</desc>
    <category lang="ba">Informativni</category>
    <icon src="https://images2.imgbox.com/7e/2e/EnmzsW0o_o.png" />
  </programme>
  <programme channel="AlJazeeraBalkans.qa" start="20230723190000 +0100" stop="20230723190500 +0100">
    <title lang="ba">Kratke vijesti u 19</title>
    <desc lang="ba">Al Jazeera Balkans međunarodna je televizijska postaja mreže Al Jazeera. Dvadeset sati sadržaja postaja samostalno proizvodi na bošnjačkom, hrvatskom i srpskom jeziku, dok ostatak čini program Al Jazeere English. Show Id: 23060296</desc>
    <category lang="ba">Informativni</category>
    <icon src="https://images2.imgbox.com/7e/2e/EnmzsW0o_o.png" />
  </programme>
  <programme channel="AlJazeeraBalkans.qa" start="20230723190500 +0100" stop="20230723200000 +0100">
    <title lang="ba">SportDoc - Zubandan</title>
    <desc lang="ba">Al Jazeera Balkans međunarodna je televizijska postaja mreže Al Jazeera. Dvadeset sati sadržaja postaja samostalno proizvodi na bošnjačkom, hrvatskom i srpskom jeziku, dok ostatak čini program Al Jazeere English. Show Id: 23060299</desc>
    <category lang="ba">Dokumentarni</category>
    <icon src="https://images2.imgbox.com/7e/2e/EnmzsW0o_o.png" />
  </programme>
  <programme channel="AlJazeeraBalkans.qa" start="20230723200000 +0100" stop="20230723210000 +0100">
    <title lang="ba">Vijesti u 20</title>
    <desc lang="ba">Al Jazeera Balkans međunarodna je televizijska postaja mreže Al Jazeera. Dvadeset sati sadržaja postaja samostalno proizvodi na bošnjačkom, hrvatskom i srpskom jeziku, dok ostatak čini program Al Jazeere English. Show Id: 23060302</desc>
    <category lang="ba">Informativni</category>
    <icon src="https://images2.imgbox.com/7e/2e/EnmzsW0o_o.png" />
  </programme>
  <programme channel="AlJazeeraBalkans.qa" start="20230723210000 +0100" stop="20230723210100 +0100">
    <title lang="ba">Kratke vijesti u 21</title>
    <desc lang="ba">Al Jazeera Balkans međunarodna je televizijska postaja mreže Al Jazeera. Dvadeset sati sadržaja postaja samostalno proizvodi na bošnjačkom, hrvatskom i srpskom jeziku, dok ostatak čini program Al Jazeere English. Show Id: 23060305</desc>
    <category lang="ba">Informativni</category>
    <icon src="https://images2.imgbox.com/7e/2e/EnmzsW0o_o.png" />
  </programme>
  <programme channel="AlJazeeraBalkans.qa" start="20230723210100 +0100" stop="20230723213000 +0100">
    <title lang="ba">Jho Low - Lov na bjegunca</title>
    <desc lang="ba">Al Jazeera Balkans međunarodna je televizijska postaja mreže Al Jazeera. Dvadeset sati sadržaja postaja samostalno proizvodi na bošnjačkom, hrvatskom i srpskom jeziku, dok ostatak čini program Al Jazeere English. Show Id: 23060308</desc>
    <category lang="ba">Dokumentarni</category>
    <icon src="https://images2.imgbox.com/7e/2e/EnmzsW0o_o.png" />
  </programme>
  <programme channel="AlJazeeraBalkans.qa" start="20230723213000 +0100" stop="20230723220000 +0100">
    <title lang="ba">AJ Svijet 2023</title>
    <desc lang="ba">Al Jazeera Balkans međunarodna je televizijska postaja mreže Al Jazeera. Dvadeset sati sadržaja postaja samostalno proizvodi na bošnjačkom, hrvatskom i srpskom jeziku, dok ostatak čini program Al Jazeere English. Show Id: 23060311</desc>
    <category lang="ba">Informativni</category>
    <icon src="https://images2.imgbox.com/7e/2e/EnmzsW0o_o.png" />
  </programme>
  <programme channel="AlJazeeraBalkans.qa" start="20230723220000 +0100" stop="20230723230000 +0100">
    <title lang="ba">Vijesti u 22</title>
    <desc lang="ba">Al Jazeera Balkans međunarodna je televizijska postaja mreže Al Jazeera. Dvadeset sati sadržaja postaja samostalno proizvodi na bošnjačkom, hrvatskom i srpskom jeziku, dok ostatak čini program Al Jazeere English. Show Id: 23060315</desc>
    <category lang="ba">Informativni</category>
    <icon src="https://images2.imgbox.com/7e/2e/EnmzsW0o_o.png" />
  </programme>
  <programme channel="AlJazeeraBalkans.qa" start="20230723230000 +0100" stop="20230723230500 +0100">
    <title lang="ba">Kratke vijesti u 23</title>
    <desc lang="ba">Al Jazeera Balkans međunarodna je televizijska postaja mreže Al Jazeera. Dvadeset sati sadržaja postaja samostalno proizvodi na bošnjačkom, hrvatskom i srpskom jeziku, dok ostatak čini program Al Jazeere English. Show Id: 23060318</desc>
    <category lang="ba">Informativni</category>
    <icon src="https://images2.imgbox.com/7e/2e/EnmzsW0o_o.png" />
  </programme>
  <programme channel="AlJazeeraBalkans.qa" start="20230723230500 +0100" stop="20230724000000 +0100">
    <title lang="ba">SportDoc - Zubandan</title>
    <desc lang="ba">Al Jazeera Balkans međunarodna je televizijska postaja mreže Al Jazeera. Dvadeset sati sadržaja postaja samostalno proizvodi na bošnjačkom, hrvatskom i srpskom jeziku, dok ostatak čini program Al Jazeere English. Show Id: 23060321</desc>
    <category lang="ba">Dokumentarni</category>
    <icon src="https://images2.imgbox.com/7e/2e/EnmzsW0o_o.png" />
  </programme>
  <programme channel="AlJazeeraBalkans.qa" start="20230724000000 +0100" stop="20230724003000 +0100">
    <title lang="ba">Vijesti u 00</title>
    <desc lang="ba">Al Jazeera Balkans međunarodna je televizijska postaja mreže Al Jazeera. Dvadeset sati sadržaja postaja samostalno proizvodi na bošnjačkom, hrvatskom i srpskom jeziku, dok ostatak čini program Al Jazeere English. Show Id: 23060324</desc>
    <category lang="ba">Informativni</category>
    <icon src="https://images2.imgbox.com/7e/2e/EnmzsW0o_o.png" />
  </programme>
  <programme channel="AlJazeeraBalkans.qa" start="20230724003000 +0100" stop="20230724010000 +0100">
    <title lang="ba">AJ Svijet 2023</title>
    <desc lang="ba">Al Jazeera Balkans međunarodna je televizijska postaja mreže Al Jazeera. Dvadeset sati sadržaja postaja samostalno proizvodi na bošnjačkom, hrvatskom i srpskom jeziku, dok ostatak čini program Al Jazeere English. Show Id: 23060327</desc>
    <category lang="ba">Informativni</category>
    <icon src="https://images2.imgbox.com/7e/2e/EnmzsW0o_o.png" />
  </programme>
  <programme channel="AlJazeeraBalkans.qa" start="20230724010000 +0100" stop="20230724013000 +0100">
    <title lang="ba">Odabrane priče</title>
    <desc lang="ba">Al Jazeera Balkans međunarodna je televizijska postaja mreže Al Jazeera. Dvadeset sati sadržaja postaja samostalno proizvodi na bošnjačkom, hrvatskom i srpskom jeziku, dok ostatak čini program Al Jazeere English. Show Id: 23060329</desc>
    <category lang="ba">Dokumentarni</category>
    <icon src="https://images2.imgbox.com/7e/2e/EnmzsW0o_o.png" />
  </programme>
  <programme channel="AlJazeeraBalkans.qa" start="20230724013000 +0100" stop="20230724020000 +0100">
    <title lang="ba">Putnici</title>
    <desc lang="ba">Al Jazeera Balkans međunarodna je televizijska postaja mreže Al Jazeera. Dvadeset sati sadržaja postaja samostalno proizvodi na bošnjačkom, hrvatskom i srpskom jeziku, dok ostatak čini program Al Jazeere English. Show Id: 23060332</desc>
    <category lang="ba">Dokumentarni</category>
    <icon src="https://images2.imgbox.com/7e/2e/EnmzsW0o_o.png" />
  </programme>
  <programme channel="AlJazeeraBalkans.qa" start="20230724020000 +0100" stop="20230724030000 +0100">
    <title lang="ba">Regioskop - Iskovane u vatri</title>
    <desc lang="ba">Al Jazeera Balkans međunarodna je televizijska postaja mreže Al Jazeera. Dvadeset sati sadržaja postaja samostalno proizvodi na bošnjačkom, hrvatskom i srpskom jeziku, dok ostatak čini program Al Jazeere English. Show Id: 23060334</desc>
    <category lang="ba">Dokumentarni</category>
    <icon src="https://images2.imgbox.com/7e/2e/EnmzsW0o_o.png" />
  </programme>
  <programme channel="AlJazeeraBalkans.qa" start="20230724030000 +0100" stop="20230724033000 +0100">
    <title lang="ba">AJ Svijet 2023</title>
    <desc lang="ba">Al Jazeera Balkans međunarodna je televizijska postaja mreže Al Jazeera. Dvadeset sati sadržaja postaja samostalno proizvodi na bošnjačkom, hrvatskom i srpskom jeziku, dok ostatak čini program Al Jazeere English. Show Id: 23060337</desc>
    <category lang="ba">Informativni</category>
    <icon src="https://images2.imgbox.com/7e/2e/EnmzsW0o_o.png" />
  </programme>
  <programme channel="AlJazeeraBalkans.qa" start="20230724033000 +0100" stop="20230724040000 +0100">
    <title lang="ba">Linije razdvajanja</title>
    <desc lang="ba">Al Jazeera Balkans međunarodna je televizijska postaja mreže Al Jazeera. Dvadeset sati sadržaja postaja samostalno proizvodi na bošnjačkom, hrvatskom i srpskom jeziku, dok ostatak čini program Al Jazeere English. Show Id: 23060340</desc>
    <category lang="ba">Dokumentarni</category>
    <icon src="https://images2.imgbox.com/7e/2e/EnmzsW0o_o.png" />
  </programme>
  <programme channel="AlJazeeraBalkans.qa" start="20230724040000 +0100" stop="20230724073000 +0100">
    <title lang="ba">Al Jazeera English</title>
    <desc lang="ba">Al Jazeera Balkans međunarodna je televizijska postaja mreže Al Jazeera. Dvadeset sati sadržaja postaja samostalno proizvodi na bošnjačkom, hrvatskom i srpskom jeziku, dok ostatak čini program Al Jazeere English. Show Id: 23060343</desc>
    <category lang="ba">ostalo</category>
    <icon src="https://images2.imgbox.com/7e/2e/EnmzsW0o_o.png" />
  </programme>
</tv>

