<?xml version="1.0" encoding="UTF-8"?>
<!DOCTYPE tv SYSTEM "xmltv.dtd">

<tv source-info-name="TV" source-info-url="iskon_tv_epg.xml">
  <channel id="StarMovies.hr">
    <display-name>Star Movies</display-name>
    <url>https://www.iskon.hr/</url>
    <icon src="https://images2.imgbox.com/35/1b/Y6eSWKO0_o.png" />
  </channel>
  <programme channel="StarMovies.hr" start="20231226041500 +0100" stop="20231226060000 +0100">
    <title lang="hr">Veliko nebo</title>
    <desc lang="hr">Big Sky - (S02, E16, igrana serija, SAD, 2022) Druga sezona prati privatne detektive Cassie Dewell i Jenny Hoyt, dok istražuju olupinu automobila pored gada Helena u Montani, te uskoro otkrivaju da slučaj nije baš tako jednostavan kako se na prvi pogled čini.
 R.: Christina Voros
 Ul.: Katheryn Winnick (Jenny Hoyt), Kylie Bunbury (Cassie Dewell), Dedee Pfeiffer (Denise Brisbane), Anja Savcic (Scarlet Leyendecker), Janina Gavankar (Ren Bhullar)...</desc>
    <category lang="hr">Movies</category>
    <icon src="https://tv.iskon.hr/var/ezdemo_site/storage/epg/111285/4337eac8fdab13085d846fe84ae67232.jpg" />
  </programme>
  <programme channel="StarMovies.hr" start="20231226060000 +0100" stop="20231226064000 +0100">
    <title lang="hr">Nevolje s mr. Beanom</title>
    <desc lang="hr">Mr. Bean - (S01, E04, humor. serija, Engleska, 1991) Humoristična serija "Mr. Bean" donosi priču o muškarcu koji je zapravo dijete u tijelu odrasle osobe. Njegova je svakodnevica puna smiješnih situacija jer često stvari izmaknu kontroli. Sve što napravi izaziva smijeh, bilo da je riječ o interakciji s drugim ljudima ili jednostavno situacijama u kojim se nađe. Iako rijetko kad priča, uz njegove nam avanture nikad nije dosadno!
 R.: Paul Weiland
 Ul.: Rowan Atkinson (Mr Bean), Nick Hancock (The Camera Thief), Robin Driscoll (The Police Sergeant), Dursley McLinden (The Shoe Salesman), Matilda Ziegler (The Girlfriend)...</desc>
    <category lang="hr">Movies</category>
    <icon src="https://tv.iskon.hr/var/ezdemo_site/storage/epg/111285/db07f4b91107f8e7f849a0fa05281620.jpg" />
  </programme>
  <programme channel="StarMovies.hr" start="20231226064000 +0100" stop="20231226082500 +0100">
    <title lang="hr">Nisam spremna za blagdane</title>
    <desc lang="hr">I'm Not Ready for Christmas - (film, SAD, 2015) Hollyn svijet se okrene naglavačke kad Djed Božićnjak ispuni želju njezinoj nećakinji - da Holly prestane lagati. Dok su joj karijera i ljubavni život u potpunom rasulu, ona mora naučiti kako prosuditi što je istina i što je ispravno.
 R.: Sam Irvin
 Ul.: Alicia Witt (Holly Nolan), George Stults (Drew Vincent), Brigid Brannagh (Rose Geller), Mia Bagley (Anna Gellar), Dan Lauria (Santa)...</desc>
    <category lang="hr">Movies</category>
    <icon src="https://tv.iskon.hr/var/ezdemo_site/storage/epg/111285/5ce1e59bc710ab7bcdd20ceb2179dcdb.jpg" />
  </programme>
  <programme channel="StarMovies.hr" start="20231226082500 +0100" stop="20231226102000 +0100">
    <title lang="hr">Najslađe stvorenje</title>
    <desc lang="hr">The Sweetest Thing - (romant. komedija, SAD, 2002) Christina Walters magnet je za muškarce koji traže samo kratkoročne afere bez obaveza. Sve se promijeni kad u diskoteci upozna svog muškarca iz snova Petera i otputuje za njim na vjenčanje jer je to jedino što zna o njemu. Djevojke kreću u avanturu, a na turbulentnom putovanju iz očekuju mnoga iznenađenja, a najveće je u crkvi.
 R.: Roger Kumble
 Ul.: Cameron Diaz (Christina Walters), Thomas Jane (Peter Donahue), Christina Applegate (Courtney Rockliffe), Lillian Adams (Aunt Frida), Bryan Anthony (Geeky Guy)...</desc>
    <category lang="hr">Movies</category>
    <icon src="https://tv.iskon.hr/var/ezdemo_site/storage/epg/111285/dc5857a2ab4c137c36734cce3f31e13c.jpg" />
  </programme>
  <programme channel="StarMovies.hr" start="20231226102000 +0100" stop="20231226124000 +0100">
    <title lang="hr">Pet legendi</title>
    <desc lang="hr">Rise of the Guardians - (anim. film, SAD, 2012) Zabavna čarobna priča o legendarnim čuvarima: Jacku Frostu, Uskršnjem zecu, Djedu Božićnjaku i Zubić vili - po prvi put okupljenima zajedno. Kad strašni Pitch zaprijeti da će podjarmiti svijet, na našim je junacima da zaštite nade i snove djece.
 R.: Peter Ramsey
 Ul.: Chris Pine (Jack Frost), Alec Baldwin (North), Jude Law (Pitch), Isla Fisher (Tooth), Hugh Jackman (Bunny)...</desc>
    <category lang="hr">Movies</category>
    <icon src="https://tv.iskon.hr/var/ezdemo_site/storage/epg/111285/3ed859f302c4f2392951d8d300caee0f.jpg" />
  </programme>
  <programme channel="StarMovies.hr" start="20231226124000 +0100" stop="20231226150500 +0100">
    <title lang="hr">Indiana Jones i otimači izgubljenog kovčega</title>
    <desc lang="hr">Raiders of the Lost Ark - (pust. film, SAD, 1981) Američka vlada unajmila je arheologa i pustolova Indianu Jonesa da pronađe Kovčeg Saveza prije nego to učine nacisti.
 R.: Steven Spielberg
 Ul.: Harrison Ford (Indy), Karen Allen (Marion), Paul Freeman (Belloq), Denholm Elliott (Brody), Ronald Lacey (Toht)...</desc>
    <category lang="hr">Movies</category>
    <icon src="https://tv.iskon.hr/var/ezdemo_site/storage/epg/111285/c361724443c01d886048c8d72d9467bb.jpg" />
  </programme>
  <programme channel="StarMovies.hr" start="20231226150500 +0100" stop="20231226175000 +0100">
    <title lang="hr">Kapetan Kuka</title>
    <desc lang="hr">Hook - (pust. film, SAD, 1991) Petar Pan je odrastao i postao opasan odvjetnik, oženjen s Wendy, unukom Kapetana Kuke. Kapetan Kuka otme njegovu djecu, a Petar se sa Zvončicom vraća u Nigdjezemsku gdje se mora prisjetiti kako ponovno biti Petar Pan da bi spasio svoju djecu.
 R.: Steven Spielberg
 Ul.: Dustin Hoffman (Captain Hook), Robin Williams (Peter Pan / Peter Banning), Julia Roberts (Tinkerbell), Bob Hoskins (Smee), Maggie Smith (Granny Wendy)...</desc>
    <category lang="hr">Movies</category>
    <icon src="https://tv.iskon.hr/var/ezdemo_site/storage/epg/111285/23bd13b2aaf1c141fa59a4a4618ba148.jpg" />
  </programme>
  <programme channel="StarMovies.hr" start="20231226175000 +0100" stop="20231226200500 +0100">
    <title lang="hr">Pogodi tko dolazi na večeru</title>
    <desc lang="hr">Guess Who - (komedija, SAD, 2005) Sarkastični afroamerički otac ima štošta reći o svojoj kćeri koja se želi udati za bijelca.
 R.: Kevin Rodney Sullivan
 Ul.: Ashton Kutcher (Simon Green), Bernie Mac (Percy Jones), Zoe Saldaña (Theresa Jones), Judith Scott (Marilyn Jones), Hal Williams (Howard Jones)...</desc>
    <category lang="hr">Movies</category>
    <icon src="https://tv.iskon.hr/var/ezdemo_site/storage/epg/111285/d53810a512dc1276abe252f6737f4338.jpg" />
  </programme>
  <programme channel="StarMovies.hr" start="20231226200500 +0100" stop="20231226210000 +0100">
    <title lang="hr">Veliko nebo</title>
    <desc lang="hr">Big Sky - (S02, E17, igrana serija, SAD, 2022) Druga sezona prati privatne detektive Cassie Dewell i Jenny Hoyt, dok istražuju olupinu automobila pored gada Helena u Montani, te uskoro otkrivaju da slučaj nije baš tako jednostavan kako se na prvi pogled čini.

 Ul.: Katheryn Winnick (Jenny Hoyt), Kylie Bunbury (Cassie Dewell), Brian Geraghty (Ronald Pergman), Dedee Pfeiffer (Denise Brisbane), Anja Savcic (Scarlet Leyendecker)...</desc>
    <category lang="hr">Movies</category>
    <icon src="https://tv.iskon.hr/var/ezdemo_site/storage/epg/111285/99ff306a4ad84428de2447477f9c341c.jpg" />
  </programme>
  <programme channel="StarMovies.hr" start="20231226210000 +0100" stop="20231226232500 +0100">
    <title lang="hr">Indiana Jones i ukleti hram</title>
    <desc lang="hr">Indiana Jones and the Temple of Doom - (pust. film, SAD, 1984) Nakon dolaska u Indiju, Indianu Jones očajni seljani mole da pronađe mistični kamen. On pristane, te nabasa na tajni kult koji u katakombama drevne palače kuje grozan plan.
 R.: Steven Spielberg
 Ul.: Harrison Ford (Indiana Jones), Kate Capshaw (Willie Scott), Ke Huy Quan (Short Round), Amrish Puri (Mola Ram), Roshan Seth (Chattar Lal)...</desc>
    <category lang="hr">Movies</category>
    <icon src="https://tv.iskon.hr/var/ezdemo_site/storage/epg/111285/a314bfc9760fdeb69ae8acae7d9fc330.jpg" />
  </programme>
  <programme channel="StarMovies.hr" start="20231226232500 +0100" stop="20231227012500 +0100">
    <title lang="hr">Senzacionalna vijest</title>
    <desc lang="hr">Scoop - (komedija, Engleska, 2006) Student novinarstva, Amerikanac, u Londonu nailazi na veliku priču te započinje ljubavnu vezu s aristrokratkinjom, dok se klupko razmotava.
 R.: Woody Allen
 Ul.: Scarlett Johansson (Sondra Pransky), Hugh Jackman (Peter Lyman), Woody Allen (Sid Waterman), Ian McShane (Joe Strombel), Charles Dance (Mr. Malcolm)...</desc>
    <category lang="hr">Movies</category>
    <icon src="https://tv.iskon.hr/var/ezdemo_site/storage/epg/111285/33ba11fdee84330a2739d414f452cc38.jpg" />
  </programme>
  <programme channel="StarMovies.hr" start="20231227012500 +0100" stop="20231227034500 +0100">
    <title lang="hr">Duboki udar</title>
    <desc lang="hr">Deep Impact - (film katastrofe, SAD, 1998) Ako se komet ne može uništiti prije sudara sa Zemljom, preživjet će samo oni kojima će biti dopušteno ući u skloništa. Tko će preživjeti?
 R.: Mimi Leder
 Ul.: Robert Duvall (Spurgeon Tanner), Téa Leoni (Jenny Lerner), Elijah Wood (Leo Beiderman), Vanessa Redgrave (Robin Lerner), Morgan Freeman (Prezident Beck)...</desc>
    <category lang="hr">Movies</category>
    <icon src="https://tv.iskon.hr/var/ezdemo_site/storage/epg/111285/19ca02ed196b610c055ef87788f656b6.jpg" />
  </programme>
  <programme channel="StarMovies.hr" start="20231227034500 +0100" stop="20231227042500 +0100">
    <title lang="hr">Veliko nebo</title>
    <desc lang="hr">Big Sky - (S02, E17, igrana serija, SAD, 2022) Druga sezona prati privatne detektive Cassie Dewell i Jenny Hoyt, dok istražuju olupinu automobila pored gada Helena u Montani, te uskoro otkrivaju da slučaj nije baš tako jednostavan kako se na prvi pogled čini.

 Ul.: Katheryn Winnick (Jenny Hoyt), Kylie Bunbury (Cassie Dewell), Brian Geraghty (Ronald Pergman), Dedee Pfeiffer (Denise Brisbane), Anja Savcic (Scarlet Leyendecker)...</desc>
    <category lang="hr">Movies</category>
    <icon src="https://tv.iskon.hr/var/ezdemo_site/storage/epg/111285/7aec5f9a879d6285b41184afc5fce751.jpg" />
  </programme>
  <programme channel="StarMovies.hr" start="20231227042500 +0100" stop="20231227060000 +0100">
    <title lang="hr">Nevolje s mr. Beanom</title>
    <desc lang="hr">Mr. Bean - (S01, E04, humor. serija, Engleska, 1991) Humoristična serija "Mr. Bean" donosi priču o muškarcu koji je zapravo dijete u tijelu odrasle osobe. Njegova je svakodnevica puna smiješnih situacija jer često stvari izmaknu kontroli. Sve što napravi izaziva smijeh, bilo da je riječ o interakciji s drugim ljudima ili jednostavno situacijama u kojim se nađe. Iako rijetko kad priča, uz njegove nam avanture nikad nije dosadno!
 R.: Paul Weiland
 Ul.: Rowan Atkinson (Mr Bean), Nick Hancock (The Camera Thief), Robin Driscoll (The Police Sergeant), Dursley McLinden (The Shoe Salesman), Matilda Ziegler (The Girlfriend)...</desc>
    <category lang="hr">Movies</category>
    <icon src="https://tv.iskon.hr/var/ezdemo_site/storage/epg/111285/926cb7972988dd81a8ba204102385d01.jpg" />
  </programme>
</tv>

