<?xml version="1.0" encoding="UTF-8"?>
<!DOCTYPE tv SYSTEM "xmltv.dtd">
<tv generator-info-name="TVCTC" source-info-url="https://www.redbull.com/int-en/channels/best-of-red-bull-stream" time-created="2025-05-31 22:55:00">
  <channel id="redbull.com">
    <display-name>Red Bull TV</display-name>
    <icon src="https://images2.imgbox.com/66/de/t9thE5Ji_o.png"/>
  </channel>
  <programme channel="redbull.com" start="20250531175717+0000" stop="20250531200249+0000">
    <title lang="en">Crankworx: RockShox Downhill -- Cairns</title>
    <desc lang="en">It’s high-speed action as top MTB riders take on the downhill challenge at Crankworx 2025 in Cairns.</desc>
    <category lang="en">MTB</category>
    <icon src="https://img.redbull.com/images/c_fill,w_600,h_400/q_auto,f_auto/redbullcom/2025/4/2/jvkwxiz7xww9slt0cih1/downhill-crankworx-cairns-2023"/>
  </programme>
  <programme channel="redbull.com" start="20250531172841+0000" stop="20250531175717+0000">
    <title lang="en">Best moments of 2023</title>
    <desc lang="en">From Xross Hard Enduro to GetzenRodeo, relive the best moments from the 2023 Hard Enduro World Championship.</desc>
    <category lang="en">Enduro</category>
    <icon src="https://img.redbull.com/images/c_fill,w_600,h_400/q_auto,f_auto/redbullcom/2023/12/21/cbofzivks1dlqjaft3kb/manuel-lettenbichler-red-bull-outliers-2023"/>
  </programme>
  <programme channel="redbull.com" start="20250531203049+0000" stop="20250531205727+0000">
    <title lang="en">Abestone Hard Enduro recap</title>
    <desc lang="en">In a new race for fans to enjoy, two days of action will culminate with 50 riders battling for the top prize.</desc>
    <category lang="en">Enduro</category>
    <icon src="https://img.redbull.com/images/c_fill,w_600,h_400/q_auto,f_auto/redbullcom/2021/4/16/d4ca8xdn4yrlgswnwg7k/fim-round-3-abestone-hard-enduro-art"/>
  </programme>
  <programme channel="redbull.com" start="20250531205727+0000" stop="20250531212349+0000">
    <title lang="en">DH recap show – Lenzerheide </title>
    <desc lang="en">Catch up on all the DH action from Lenzerheide, the halfway point of the UCI Mountain Bike World Cup 2022.</desc>
    <category lang="en">Bike</category>
    <icon src="https://img.redbull.com/images/c_fill,w_600,h_400/q_auto,f_auto/redbullcom/2022/7/21/z6bzdps7pou5qo2kfvrg/uci-world-cup-lenzerheide-2022-dh-myriam-nicole-rachel-atherton"/>
  </programme>
  <programme channel="redbull.com" start="20250531212349+0000" stop="20250531221559+0000">
    <title lang="en">Abu Dhabi Desert Challenge 2024 highlights</title>
    <desc lang="en">Round 2 of the Abu Dhabi Desert Challenge offers challenging sand dunes and baking heat in remote UAE deserts.</desc>
    <category lang="en">Sport</category>
    <icon src="https://img.redbull.com/images/c_fill,w_600,h_400/q_auto,f_auto/redbullcom/2024/3/7/cjglt0voraiqyycemrmx/rokas-baciuska-abu-dhabi-desert-challenge-2024"/>
  </programme>
  <programme channel="redbull.com" start="20250531221559+0000" stop="20250531223135+0000">
    <title lang="en">Festival highlights</title>
    <desc lang="en">Cars and motorbikes race up a hill, and fans can also enjoy a rally stage, classic cars and Red Arrows demos.</desc>
    <category lang="en">WRC</category>
    <icon src="https://img.redbull.com/images/c_fill,w_600,h_400/q_auto,f_auto/redbullcom/tv/FO-21415XT21BH11/FO-21415XT21BH11-featureMedia"/>
  </programme>
  <programme channel="redbull.com" start="20250531223135+0000" stop="20250531225338+0000">
    <title lang="en">Abu Dhabi Desert Challenge</title>
    <desc lang="en">The legendary Abu Dhabi Desert Challenge is one of the world’s most prestigious cross country rallies.</desc>
    <category lang="en">Rally Raid</category>
    <icon src="https://img.redbull.com/images/c_fill,w_600,h_400/q_auto,f_auto/redbullcom/2021/11/17/wuv1xmlzqriqxncfzxzn/cross-country-rallies-world-cup-s2021-e4-abu-dhabi-desert-challenge-art"/>
  </programme>
  <programme channel="redbull.com" start="20250531225338+0000" stop="20250531232110+0000">
    <title lang="en">Check out this crazy new motorsport</title>
    <desc lang="en">Welcome to the dizzying, squealing rage of South Africa’s adrenaline-sparking motorsport: spinning.</desc>
    <category lang="en">Drifting</category>
    <icon src="https://img.redbull.com/images/c_fill,w_600,h_400/q_auto,f_auto/redbullcom/2020/8/25/upmdrn93p8d1gfdebtxr/red-bull-shay-imoto-2019-art"/>
  </programme>
  <programme channel="redbull.com" start="20250531232110+0000" stop="20250531233143+0000">
    <title lang="en">Red Bull Flugtag </title>
    <desc lang="en">Red Bull TV programme</desc>
    <category lang="en">Red Bull Flugtag</category>
    <icon src="https://img.redbull.com/images/c_fill,w_600,h_400/q_auto,f_auto/redbullcom/2024/1/3/r532oyzhf9kijbswimef/participants"/>
  </programme>
  <programme channel="redbull.com" start="20250531233143+0000" stop="20250531234143+0000">
    <title lang="en">2018's best runs</title>
    <desc lang="en">Italian bagpipes and South Africa's fastest Stone Age soapbox made the cut among 2018's very best runs.</desc>
    <category lang="en">Red Bull Soapbox Race</category>
    <icon src="https://img.redbull.com/images/c_fill,w_600,h_400/q_auto,f_auto/redbullcom/2022/7/28/pm6zgr2tqmnkc2jfehhf/red-bull-soapbox-race-rome-2018"/>
  </programme>
  <programme channel="redbull.com" start="20250531234143+0000" stop="20250601001107+0000">
    <title lang="en">Dune racing with Kirsten Landman</title>
    <desc lang="en">Jason and Nick track down endurance motorcyclist Kirsten Landman on sun-scorched dunes in Cape Town.</desc>
    <category lang="en">Motoring</category>
    <icon src="https://img.redbull.com/images/c_fill,w_600,h_400/q_auto,f_auto/redbullcom/2023/2/6/brsrbtjamhd6bhvm5npv/jason-goliath-and-kirsten-landman-giving-it-gears"/>
  </programme>
  <programme channel="redbull.com" start="20250601001107+0000" stop="20250601010343+0000">
    <title lang="en">Brad Binder: Becoming 33</title>
    <desc lang="en">Brad Binder has earned his shot at MotoGP™ glory – see him take on the monumental challenge.</desc>
    <category lang="en">MotoGP</category>
    <icon src="https://img.redbull.com/images/c_fill,w_600,h_400/q_auto,f_auto/redbullcom/2020/8/31/ex1kbwbekyroewn8fdmk/brad-binder-road-to-motogp-hero-art"/>
  </programme>
  <programme channel="redbull.com" start="20250601010343+0000" stop="20250601013028+0000">
    <title lang="en">Best of Bolton – Sea to Sky</title>
    <desc lang="en">Ride with extreme enduro rider Paul Bolton alongside Hard Enduro heroes fighting for the win at Sea to Sky.</desc>
    <category lang="en">Enduro</category>
    <icon src="https://img.redbull.com/images/c_fill,w_600,h_400/q_auto,f_auto/redbullcom/2024/10/14/hw7cwha55y91tjmm5ugt/manuel-lettenbichler-fim-hard-enduro-sea-to-sky-2024-turkey"/>
  </programme>
  <programme channel="redbull.com" start="20250601013028+0000" stop="20250601021504+0000">
    <title lang="en">Kasso 2024 – part 1 </title>
    <desc lang="en">Guest competitors Leo Romero, Madars Apse and Wes Kremer take on wild and obstacle-laden skate courses.</desc>
    <category lang="en">Skateboarding</category>
    <icon src="https://img.redbull.com/images/c_fill,w_600,h_400/q_auto,f_auto/redbullcom/2024/10/22/rkp9d9ninbxkvmi4e8rp/madars-apse-kasso-japan-2024"/>
  </programme>
  <programme channel="redbull.com" start="20250601021504+0000" stop="20250601025915+0000">
    <title lang="en">Kasso 2024 – part 2</title>
    <desc lang="en">Skate pros Madars Apse, Wes Kremer, Leo Romero and the local rippers take on the final two challenges.</desc>
    <category lang="en">Skateboarding</category>
    <icon src="https://img.redbull.com/images/c_fill,w_600,h_400/q_auto,f_auto/redbullcom/2024/10/22/l6xnhbqc6wz7j3opais2/madars-apse-kasso-japan-2024"/>
  </programme>
  <programme channel="redbull.com" start="20250601025915+0000" stop="20250601034401+0000">
    <title lang="en">WSL Lexus Pipe Pro wrap show</title>
    <desc lang="en">Barron Mamiya and Tyler Wright won the Lexus Pipe Pro. The WSL broadcast crew break down how it went down.</desc>
    <category lang="en">Surfing</category>
    <icon src="https://img.redbull.com/images/c_fill,w_600,h_400/q_auto,f_auto/redbullcom/2025/2/10/yrvnhgiroegdz9l679mn/molly-picklum-semifinals-lexus-pipe-pro-2025"/>
  </programme>
  <programme channel="redbull.com" start="20250601034401+0000" stop="20250601042811+0000">
    <title lang="en">WSL Abu Dhabi Pro wrap show</title>
    <desc lang="en">The WSL commentary crew review all of the action after Caitlin Simmers's and Italo Ferreira's victories.</desc>
    <category lang="en">Surfing</category>
    <icon src="https://img.redbull.com/images/c_fill,w_600,h_400/q_auto,f_auto/redbullcom/2025/2/19/grgodpvyqhg2grunxuqy/kanoa-igarashi-surfing-surf-abu-dhabi-pro-quarter-finals-hudayriyat-island-abu-dhabi-united-arab-emirates"/>
  </programme>
  <programme channel="redbull.com" start="20250601042811+0000" stop="20250601051222+0000">
    <title lang="en">WSL MEO Rip Curl Pro Portugal wrap show</title>
    <desc lang="en">Who was crowned king and queen of Supertubos? Watch highlights of finals day at MEO Rip Curl Pro Portugal. </desc>
    <category lang="en">Surfing</category>
    <icon src="https://img.redbull.com/images/c_fill,w_600,h_400/q_auto,f_auto/redbullcom/2025/3/24/jz2yrcmch22rarlhzk2t/caroline-marks-wsl-meo-rip-curl-pro-portugal-2025"/>
  </programme>
  <programme channel="redbull.com" start="20250601051222+0000" stop="20250601055622+0000">
    <title lang="en">WSL Surf City El Salvador Pro wrap show</title>
    <desc lang="en">The WSL commentary crew break down the 2025 Surf City El Salvador Pro’s winners and losers.</desc>
    <category lang="en">Surfing</category>
    <icon src="https://img.redbull.com/images/c_fill,w_600,h_400/q_auto,f_auto/redbullcom/2025/4/14/popwkhscpmprophqwshu/jordy-smith-wsl-surf-city-el-salvador-2025"/>
  </programme>
  <programme channel="redbull.com" start="20250601055622+0000" stop="20250601060000+0000">
    <title lang="en">Kade Edwards destroys Dyfi Bike Park</title>
    <desc lang="en">Enjoy the sound of speed as British mountain bike rider Kade Edwards rips up Dyfi Bike Park in Wales. </desc>
    <category lang="en">MTB</category>
    <icon src="https://img.redbull.com/images/c_fill,w_600,h_400/q_auto,f_auto/redbullcom/2024/2/12/doge7u1jj7vxmsg8m1sq/kade-edwards-dyfi-bike-park"/>
  </programme>
  <programme channel="redbull.com" start="20250601025915+0000" stop="20250601034401+0000">
    <title lang="en">WSL Lexus Pipe Pro wrap show</title>
    <desc lang="en">Barron Mamiya and Tyler Wright won the Lexus Pipe Pro. The WSL broadcast crew break down how it went down.</desc>
    <category lang="en">Surfing</category>
    <icon src="https://img.redbull.com/images/c_fill,w_600,h_400/q_auto,f_auto/redbullcom/2025/2/10/yrvnhgiroegdz9l679mn/molly-picklum-semifinals-lexus-pipe-pro-2025"/>
  </programme>
  <programme channel="redbull.com" start="20250601034401+0000" stop="20250601042811+0000">
    <title lang="en">WSL Abu Dhabi Pro wrap show</title>
    <desc lang="en">The WSL commentary crew review all of the action after Caitlin Simmers's and Italo Ferreira's victories.</desc>
    <category lang="en">Surfing</category>
    <icon src="https://img.redbull.com/images/c_fill,w_600,h_400/q_auto,f_auto/redbullcom/2025/2/19/grgodpvyqhg2grunxuqy/kanoa-igarashi-surfing-surf-abu-dhabi-pro-quarter-finals-hudayriyat-island-abu-dhabi-united-arab-emirates"/>
  </programme>
  <programme channel="redbull.com" start="20250601042811+0000" stop="20250601051222+0000">
    <title lang="en">WSL MEO Rip Curl Pro Portugal wrap show</title>
    <desc lang="en">Who was crowned king and queen of Supertubos? Watch highlights of finals day at MEO Rip Curl Pro Portugal. </desc>
    <category lang="en">Surfing</category>
    <icon src="https://img.redbull.com/images/c_fill,w_600,h_400/q_auto,f_auto/redbullcom/2025/3/24/jz2yrcmch22rarlhzk2t/caroline-marks-wsl-meo-rip-curl-pro-portugal-2025"/>
  </programme>
  <programme channel="redbull.com" start="20250601051222+0000" stop="20250601055622+0000">
    <title lang="en">WSL Surf City El Salvador Pro wrap show</title>
    <desc lang="en">The WSL commentary crew break down the 2025 Surf City El Salvador Pro’s winners and losers.</desc>
    <category lang="en">Surfing</category>
    <icon src="https://img.redbull.com/images/c_fill,w_600,h_400/q_auto,f_auto/redbullcom/2025/4/14/popwkhscpmprophqwshu/jordy-smith-wsl-surf-city-el-salvador-2025"/>
  </programme>
  <programme channel="redbull.com" start="20250601085706+0000" stop="20250601094106+0000">
    <title lang="en">WSL Rip Curl Pro Bells Beach wrap show</title>
    <desc lang="en">The WSL team analyse the highs, lows and defining moments of the 2025 Rip Curl Pro Bells Beach contest.</desc>
    <category lang="en">Surfing</category>
    <icon src="https://img.redbull.com/images/c_fill,w_600,h_400/q_auto,f_auto/redbullcom/2025/4/28/yztvuatjcnxusqdo9xja/jack-robinson-rip-curl-bells-beach-2025"/>
  </programme>
</tv>
