<?xml version="1.0" encoding="UTF-8"?>
<!DOCTYPE tv SYSTEM "xmltv.dtd">

<tv source-info-name="TV" source-info-url="tvtv_us_epg.xml">
  <channel id="Bravo.us">
    <display-name>Bravo</display-name>
    <url>tvtv.us</url>
    <icon src="https://images2.imgbox.com/12/e4/J78GlldY_o.png" />
  </channel>
  <programme channel="Bravo.us" start="20240130000000 +0100" stop="20240130010000 +0100">
    <title lang="en">Vanderpump Rules - Troll Mates</title>
    <desc lang="en">Bravo TV programme
EP016660830319</desc>
    <category lang="en">Entertainment</category>
    <icon src="https://images2.imgbox.com/12/e4/J78GlldY_o.png" />
  </programme>
  <programme channel="Bravo.us" start="20240130010000 +0100" stop="20240130020000 +0100">
    <title lang="en">Vanderpump Rules - No Home Left to Wreck</title>
    <desc lang="en">Bravo TV programme
EP016660830321</desc>
    <category lang="en">Entertainment</category>
    <icon src="https://images2.imgbox.com/12/e4/J78GlldY_o.png" />
  </programme>
  <programme channel="Bravo.us" start="20240130020000 +0100" stop="20240130030000 +0100">
    <title lang="en">Below Deck Mediterranean - Never Before Scene 816</title>
    <desc lang="en">Bravo TV programme
EP023652880246</desc>
    <category lang="en">Entertainment</category>
    <icon src="https://images2.imgbox.com/12/e4/J78GlldY_o.png" />
  </programme>
  <programme channel="Bravo.us" start="20240130030000 +0100" stop="20240130033000 +0100">
    <title lang="en">Watch What Happens Live With Andy Cohen</title>
    <desc lang="en">Bravo TV programme
EP011663332703</desc>
    <category lang="en">Entertainment</category>
    <icon src="https://images2.imgbox.com/12/e4/J78GlldY_o.png" />
  </programme>
  <programme channel="Bravo.us" start="20240130033000 +0100" stop="20240130043000 +0100">
    <title lang="en">Below Deck - No One Said This Job Was Easy</title>
    <desc lang="en">Bravo TV programme
EP015543320062</desc>
    <category lang="en">Entertainment</category>
    <icon src="https://images2.imgbox.com/12/e4/J78GlldY_o.png" />
  </programme>
  <programme channel="Bravo.us" start="20240130043000 +0100" stop="20240130053000 +0100">
    <title lang="en">Below Deck - What Happens in the Hot Tub Stays in the Hot Tub</title>
    <desc lang="en">Bravo TV programme
EP015543320063</desc>
    <category lang="en">Entertainment</category>
    <icon src="https://images2.imgbox.com/12/e4/J78GlldY_o.png" />
  </programme>
  <programme channel="Bravo.us" start="20240130053000 +0100" stop="20240130063000 +0100">
    <title lang="en">Below Deck - Hair Models and Filthy Martinis</title>
    <desc lang="en">Bravo TV programme
EP015543320064</desc>
    <category lang="en">Entertainment</category>
    <icon src="https://images2.imgbox.com/12/e4/J78GlldY_o.png" />
  </programme>
  <programme channel="Bravo.us" start="20240130063000 +0100" stop="20240130073000 +0100">
    <title lang="en">Below Deck - That Tuna Is F...</title>
    <desc lang="en">Bravo TV programme
EP015543320065</desc>
    <category lang="en">Entertainment</category>
    <icon src="https://images2.imgbox.com/12/e4/J78GlldY_o.png" />
  </programme>
  <programme channel="Bravo.us" start="20240130073000 +0100" stop="20240130083000 +0100">
    <title lang="en">Below Deck - The Freak Comes Out at Night</title>
    <desc lang="en">Bravo TV programme
EP015543320066</desc>
    <category lang="en">Entertainment</category>
    <icon src="https://images2.imgbox.com/12/e4/J78GlldY_o.png" />
  </programme>
  <programme channel="Bravo.us" start="20240130083000 +0100" stop="20240130093000 +0100">
    <title lang="en">Below Deck - The One Where the Charter Guests Almost Die</title>
    <desc lang="en">Bravo TV programme
EP015543320067</desc>
    <category lang="en">Entertainment</category>
    <icon src="https://images2.imgbox.com/12/e4/J78GlldY_o.png" />
  </programme>
  <programme channel="Bravo.us" start="20240130093000 +0100" stop="20240130100000 +0100">
    <title lang="en">Watch What Happens Live With Andy Cohen</title>
    <desc lang="en">Bravo TV programme
EP011663332703</desc>
    <category lang="en">Entertainment</category>
    <icon src="https://images2.imgbox.com/12/e4/J78GlldY_o.png" />
  </programme>
  <programme channel="Bravo.us" start="20240130100000 +0100" stop="20240130110000 +0100">
    <title lang="en">The Kelly Clarkson Show</title>
    <desc lang="en">Bravo TV programme
EP032399910816</desc>
    <category lang="en">Entertainment</category>
    <icon src="https://images2.imgbox.com/12/e4/J78GlldY_o.png" />
  </programme>
  <programme channel="Bravo.us" start="20240130110000 +0100" stop="20240130113000 +0100">
    <title lang="en">Powerful Cleaning with Shark Stratos</title>
    <desc lang="en">Bravo TV programme
SH047886000000</desc>
    <category lang="en">Entertainment</category>
    <icon src="https://images2.imgbox.com/12/e4/J78GlldY_o.png" />
  </programme>
  <programme channel="Bravo.us" start="20240130113000 +0100" stop="20240130120000 +0100">
    <title lang="en">Who Stole My Life?</title>
    <desc lang="en">Bravo TV programme
SH049445470000</desc>
    <category lang="en">Entertainment</category>
    <icon src="https://images2.imgbox.com/12/e4/J78GlldY_o.png" />
  </programme>
  <programme channel="Bravo.us" start="20240130120000 +0100" stop="20240130130000 +0100">
    <title lang="en">Vanderpump Rules - Lovestruck at the Discopussy</title>
    <desc lang="en">Bravo TV programme
EP016660830339</desc>
    <category lang="en">Entertainment</category>
    <icon src="https://images2.imgbox.com/12/e4/J78GlldY_o.png" />
  </programme>
  <programme channel="Bravo.us" start="20240130130000 +0100" stop="20240130140000 +0100">
    <title lang="en">Vanderpump Rules - Divorce Party Crashers</title>
    <desc lang="en">Bravo TV programme
EP016660830341</desc>
    <category lang="en">Entertainment</category>
    <icon src="https://images2.imgbox.com/12/e4/J78GlldY_o.png" />
  </programme>
  <programme channel="Bravo.us" start="20240130140000 +0100" stop="20240130150000 +0100">
    <title lang="en">Vanderpump Rules - Galaxy Gaslighting</title>
    <desc lang="en">Bravo TV programme
EP016660830343</desc>
    <category lang="en">Entertainment</category>
    <icon src="https://images2.imgbox.com/12/e4/J78GlldY_o.png" />
  </programme>
  <programme channel="Bravo.us" start="20240130150000 +0100" stop="20240130160000 +0100">
    <title lang="en">Vanderpump Rules - By Invitation Only</title>
    <desc lang="en">Bravo TV programme
EP016660830345</desc>
    <category lang="en">Entertainment</category>
    <icon src="https://images2.imgbox.com/12/e4/J78GlldY_o.png" />
  </programme>
  <programme channel="Bravo.us" start="20240130160000 +0100" stop="20240130170000 +0100">
    <title lang="en">Vanderpump Rules - Forbidden Fruit</title>
    <desc lang="en">Bravo TV programme
EP016660830347</desc>
    <category lang="en">Entertainment</category>
    <icon src="https://images2.imgbox.com/12/e4/J78GlldY_o.png" />
  </programme>
  <programme channel="Bravo.us" start="20240130170000 +0100" stop="20240130180000 +0100">
    <title lang="en">Vanderpump Rules - It's All Happening ... Again</title>
    <desc lang="en">Bravo TV programme
EP016660830369</desc>
    <category lang="en">Entertainment</category>
    <icon src="https://images2.imgbox.com/12/e4/J78GlldY_o.png" />
  </programme>
  <programme channel="Bravo.us" start="20240130180000 +0100" stop="20240130190000 +0100">
    <title lang="en">Vanderpump Rules - Mistress in Distress</title>
    <desc lang="en">Bravo TV programme
EP016660830371</desc>
    <category lang="en">Entertainment</category>
    <icon src="https://images2.imgbox.com/12/e4/J78GlldY_o.png" />
  </programme>
  <programme channel="Bravo.us" start="20240130190000 +0100" stop="20240130200000 +0100">
    <title lang="en">Vanderpump Rules - Beach, Don't Kill My Vibe</title>
    <desc lang="en">Bravo TV programme
EP016660830373</desc>
    <category lang="en">Entertainment</category>
    <icon src="https://images2.imgbox.com/12/e4/J78GlldY_o.png" />
  </programme>
  <programme channel="Bravo.us" start="20240130200000 +0100" stop="20240130210000 +0100">
    <title lang="en">Vanderpump Rules - Lady and the Glamp</title>
    <desc lang="en">Bravo TV programme
EP016660830375</desc>
    <category lang="en">Entertainment</category>
    <icon src="https://images2.imgbox.com/12/e4/J78GlldY_o.png" />
  </programme>
  <programme channel="Bravo.us" start="20240130210000 +0100" stop="20240130220000 +0100">
    <title lang="en">Vanderpump Rules - There's Something About Her</title>
    <desc lang="en">Bravo TV programme
EP016660830377</desc>
    <category lang="en">Entertainment</category>
    <icon src="https://images2.imgbox.com/12/e4/J78GlldY_o.png" />
  </programme>
  <programme channel="Bravo.us" start="20240130220000 +0100" stop="20240130230000 +0100">
    <title lang="en">Vanderpump Rules - #Scandoval</title>
    <desc lang="en">Bravo TV programme
EP016660830379</desc>
    <category lang="en">Entertainment</category>
    <icon src="https://images2.imgbox.com/12/e4/J78GlldY_o.png" />
  </programme>
  <programme channel="Bravo.us" start="20240130230000 +0100" stop="20240131000000 +0100">
    <title lang="en">Vanderpump Rules - Reunion Part 1</title>
    <desc lang="en">Bravo TV programme
EP016660830381</desc>
    <category lang="en">Entertainment</category>
    <icon src="https://images2.imgbox.com/12/e4/J78GlldY_o.png" />
  </programme>
  <programme channel="Bravo.us" start="20240131000000 +0100" stop="20240131010000 +0100">
    <title lang="en">Vanderpump Rules - Reunion Part 2</title>
    <desc lang="en">Bravo TV programme
EP016660830383</desc>
    <category lang="en">Entertainment</category>
    <icon src="https://images2.imgbox.com/12/e4/J78GlldY_o.png" />
  </programme>
  <channel id="SyFy.us">
    <display-name>SyFy</display-name>
    <url>tvtv.us</url>
    <icon src="https://images2.imgbox.com/a6/0c/EtJXxlV4_o.png" />
  </channel>
  <programme channel="SyFy.us" start="20240130000500 +0100" stop="20240130023800 +0100">
    <title lang="en">Cowboys &amp; Aliens (2011, Science fiction)</title>
    <desc lang="en">SyFy TV programme
MV003288660000</desc>
    <category lang="en">Sci-Fi</category>
    <icon src="https://images2.imgbox.com/a6/0c/EtJXxlV4_o.png" />
  </programme>
  <programme channel="SyFy.us" start="20240130023800 +0100" stop="20240130043000 +0100">
    <title lang="en">Cloverfield (2008, Science fiction)</title>
    <desc lang="en">SyFy TV programme
MV002051470000</desc>
    <category lang="en">Sci-Fi</category>
    <icon src="https://images2.imgbox.com/a6/0c/EtJXxlV4_o.png" />
  </programme>
  <programme channel="SyFy.us" start="20240130043000 +0100" stop="20240130063000 +0100">
    <title lang="en">Tremors (1990, Horror)</title>
    <desc lang="en">SyFy TV programme
MV000284280000</desc>
    <category lang="en">Sci-Fi</category>
    <icon src="https://images2.imgbox.com/a6/0c/EtJXxlV4_o.png" />
  </programme>
  <programme channel="SyFy.us" start="20240130063000 +0100" stop="20240130084500 +0100">
    <title lang="en">The Last Witch Hunter (2015, Fantasy)</title>
    <desc lang="en">SyFy TV programme
MV007565270000</desc>
    <category lang="en">Sci-Fi</category>
    <icon src="https://images2.imgbox.com/a6/0c/EtJXxlV4_o.png" />
  </programme>
  <programme channel="SyFy.us" start="20240130084500 +0100" stop="20240130094500 +0100">
    <title lang="en">The Twilight Zone - Jess-Belle</title>
    <desc lang="en">SyFy TV programme
EP000191100141</desc>
    <category lang="en">Sci-Fi</category>
    <icon src="https://images2.imgbox.com/a6/0c/EtJXxlV4_o.png" />
  </programme>
  <programme channel="SyFy.us" start="20240130094500 +0100" stop="20240130100000 +0100">
    <title lang="en">Devil May Care - The Influencer</title>
    <desc lang="en">SyFy TV programme
EP037222120002</desc>
    <category lang="en">Sci-Fi</category>
    <icon src="https://images2.imgbox.com/a6/0c/EtJXxlV4_o.png" />
  </programme>
  <programme channel="SyFy.us" start="20240130100000 +0100" stop="20240130103000 +0100">
    <title lang="en">Transform your home today, fast &amp; easy!</title>
    <desc lang="en">SyFy TV programme
SH037778490000</desc>
    <category lang="en">Sci-Fi</category>
    <icon src="https://images2.imgbox.com/a6/0c/EtJXxlV4_o.png" />
  </programme>
  <programme channel="SyFy.us" start="20240130103000 +0100" stop="20240130110000 +0100">
    <title lang="en">Car accident? Free Legal Consultation</title>
    <desc lang="en">SyFy TV programme
SH045753050000</desc>
    <category lang="en">Sci-Fi</category>
    <icon src="https://images2.imgbox.com/a6/0c/EtJXxlV4_o.png" />
  </programme>
  <programme channel="SyFy.us" start="20240130110000 +0100" stop="20240130113000 +0100">
    <title lang="en">Help Israel &amp; Ukraine</title>
    <desc lang="en">SyFy TV programme
SH049002530000</desc>
    <category lang="en">Sci-Fi</category>
    <icon src="https://images2.imgbox.com/a6/0c/EtJXxlV4_o.png" />
  </programme>
  <programme channel="SyFy.us" start="20240130113000 +0100" stop="20240130120000 +0100">
    <title lang="en">Who Stole My Life?</title>
    <desc lang="en">SyFy TV programme
SH049445470000</desc>
    <category lang="en">Sci-Fi</category>
    <icon src="https://images2.imgbox.com/a6/0c/EtJXxlV4_o.png" />
  </programme>
  <programme channel="SyFy.us" start="20240130120000 +0100" stop="20240130141500 +0100">
    <title lang="en">10,000 B.C. (2008, Adventure)</title>
    <desc lang="en">SyFy TV programme
MV002000840000</desc>
    <category lang="en">Sci-Fi</category>
    <icon src="https://images2.imgbox.com/a6/0c/EtJXxlV4_o.png" />
  </programme>
  <programme channel="SyFy.us" start="20240130141500 +0100" stop="20240130170000 +0100">
    <title lang="en">Snow White and the Huntsman (2012, Fantasy)</title>
    <desc lang="en">SyFy TV programme
MV003608680000</desc>
    <category lang="en">Sci-Fi</category>
    <icon src="https://images2.imgbox.com/a6/0c/EtJXxlV4_o.png" />
  </programme>
  <programme channel="SyFy.us" start="20240130170000 +0100" stop="20240130190000 +0100">
    <title lang="en">Tremors (1990, Horror)</title>
    <desc lang="en">SyFy TV programme
MV000284280000</desc>
    <category lang="en">Sci-Fi</category>
    <icon src="https://images2.imgbox.com/a6/0c/EtJXxlV4_o.png" />
  </programme>
  <programme channel="SyFy.us" start="20240130190000 +0100" stop="20240130213200 +0100">
    <title lang="en">Cowboys &amp; Aliens (2011, Science fiction)</title>
    <desc lang="en">SyFy TV programme
MV003288660000</desc>
    <category lang="en">Sci-Fi</category>
    <icon src="https://images2.imgbox.com/a6/0c/EtJXxlV4_o.png" />
  </programme>
  <programme channel="SyFy.us" start="20240130213200 +0100" stop="20240130232500 +0100">
    <title lang="en">Cloverfield (2008, Science fiction)</title>
    <desc lang="en">SyFy TV programme
MV002051470000</desc>
    <category lang="en">Sci-Fi</category>
    <icon src="https://images2.imgbox.com/a6/0c/EtJXxlV4_o.png" />
  </programme>
  <programme channel="SyFy.us" start="20240130232500 +0100" stop="20240131023000 +0100">
    <title lang="en">Troy (2004, Adventure)</title>
    <desc lang="en">SyFy TV programme
MV001475950000</desc>
    <category lang="en">Sci-Fi</category>
    <icon src="https://images2.imgbox.com/a6/0c/EtJXxlV4_o.png" />
  </programme>
</tv>

